StreamOneIONSDK/__init__.py
StreamOneIONSDK/client.py
StreamOneIONSDK/exceptions.py
StreamOneIONSDK/v1/__init__.py
StreamOneIONSDK/v1/billing/__init__.py
StreamOneIONSDK/v1/billing/billing.py
StreamOneIONSDK/v1/customers/__init__.py
StreamOneIONSDK/v1/customers/customers.py
StreamOneIONSDK/v3/__init__.py
StreamOneIONSDK/v3/customers/__init__.py
StreamOneIONSDK/v3/customers/customers.py
StreamOneIONSDK/v3/orders/__init__.py
StreamOneIONSDK/v3/orders/orders.py
StreamOneIONSDK/v3/products/__init__.py
StreamOneIONSDK/v3/products/products.py
StreamOneIONSDK/v3/reports/__init__.py
StreamOneIONSDK/v3/reports/reports.py
StreamOneIONSDK/v3/subscriptions/__init__.py
StreamOneIONSDK/v3/subscriptions/subscriptions.py
StreamOneSDK/__init__.py
StreamOneSDK/client.py
StreamOneSDK/exceptions.py
StreamOneSDK/v1/__init__.py
StreamOneSDK/v1/billing/__init__.py
StreamOneSDK/v1/billing/billing.py
StreamOneSDK/v1/customers/__init__.py
StreamOneSDK/v1/customers/customers.py
StreamOneSDK/v3/__init__.py
StreamOneSDK/v3/customers/__init__.py
StreamOneSDK/v3/customers/customers.py
StreamOneSDK/v3/orders/__init__.py
StreamOneSDK/v3/orders/orders.py
StreamOneSDK/v3/products/__init__.py
StreamOneSDK/v3/products/products.py
StreamOneSDK/v3/reports/__init__.py
StreamOneSDK/v3/reports/reports.py
StreamOneSDK/v3/subscriptions/__init__.py
StreamOneSDK/v3/subscriptions/subscriptions.py
streamoneionsdk-0.1.8.dist-info/METADATA
streamoneionsdk-0.1.8.dist-info/WHEEL
streamoneionsdk-0.1.8.dist-info/top_level.txt
streamoneionsdk-0.1.8.dist-info/RECORD
