Metadata-Version: 2.4
Name: streamOneIonSDK
Version: 0.1.8
Requires-Dist: requests
Dynamic: description
Dynamic: description-content-type
Dynamic: requires-dist
